LICENSE
MANIFEST.in
README.md
setup.py
om_simple/__init__.py
om_simple/dino.py
om_simple/img_class_head.py
om_simple/img_class_model.py
om_simple/multi_class_model.py
om_simple/randaug.py
om_simple/vision_transformer.py
om_simple.egg-info/PKG-INFO
om_simple.egg-info/SOURCES.txt
om_simple.egg-info/dependency_links.txt
om_simple.egg-info/requires.txt
om_simple.egg-info/top_level.txt
om_simple/clip/__init__.py
om_simple/clip/bpe_simple_vocab_16e6.txt.gz
om_simple/clip/clip.py
om_simple/clip/model.py
om_simple/clip/simple_tokenizer.py
om_simple/clip_multi_label_class/__init__.py
om_simple/clip_multi_label_class/model.py
om_simple/clip_multi_label_class/text_image_dm.py
om_simple/clip_multi_label_class/wrapper.py
om_simple/clip_multi_label_class/configs/RN.yaml
om_simple/clip_multi_label_class/configs/ViT.yaml
om_simple/tools/__init__.py
om_simple/tools/utils.py