Metadata-Version: 2.1
Name: om-simple
Version: 0.1.4
Summary: OM Simple
Home-page: https://www.soco.ai
Author: kyusonglee
License: UNKNOWN
Platform: UNKNOWN
Classifier: Programming Language :: Python :: 3
Classifier: License :: Free for non-commercial use
Classifier: Operating System :: OS Independent
